gitgotchi-0.1.3.dist-info/licenses/LICENSE
src/__init__.py
src/cli.py
src/db/__init__.py
src/db/migrations.py
src/db/models.py
src/db/state_manager.py
src/hooks/__init__.py
src/hooks/installer.py
src/hooks/post_commit.py
src/pet/__init__.py
src/pet/evolution.py
src/pet/renderer.py
src/pet/states.py
src/seance/__init__.py
src/seance/git_analyzer.py
src/seance/story_gen.py
src/seance/templates.py
gitgotchi-0.1.3.dist-info/METADATA
gitgotchi-0.1.3.dist-info/WHEEL
gitgotchi-0.1.3.dist-info/entry_points.txt
gitgotchi-0.1.3.dist-info/top_level.txt
gitgotchi-0.1.3.dist-info/RECORD
