Metadata-Version: 2.4
Name: gitgotchi
Version: 0.1.3
Summary: A Stardew Valley X Halloween -inspired terminal companion for your git repository
Home-page: https://github.com/yourusername/gitgotchi
Author: GitGotchi Team
Author-email: M K Sai Srikar <Srikarmks@gmail.com>
License: MIT
Project-URL: Homepage, https://github.com/Srikarmk/gitgotchi
Project-URL: Repository, https://github.com/Srikarmk/gitgotchi
Project-URL: Issues, https://github.com/Srikarmk/gitgotchi/issues
Project-URL: Documentation, https://github.com/Srikarmk/gitgotchi#readme
Keywords: git,terminal,pet,companion,stardew-valley,ai,tamagotchi,devtools,hackathon,kiro
Classifier: Development Status :: 3 - Alpha
Classifier: Intended Audience :: Developers
Classifier: Topic :: Software Development :: Version Control :: Git
Classifier: License :: OSI Approved :: MIT License
Classifier: Programming Language :: Python :: 3.10
Classifier: Programming Language :: Python :: 3.11
Classifier: Programming Language :: Python :: 3.12
Classifier: Programming Language :: Python :: 3.13
Requires-Python: >=3.10
License-File: LICENSE
Requires-Dist: rich>=13.7.0
Requires-Dist: gitpython>=3.1.40
Requires-Dist: anthropic>=0.34.0
Requires-Dist: sqlalchemy>=2.0.36
Requires-Dist: typer>=0.9.0
Requires-Dist: python-dotenv>=1.0.0
Provides-Extra: dev
Requires-Dist: pytest>=7.4.3; extra == "dev"
Requires-Dist: pytest-cov>=4.1.0; extra == "dev"
Requires-Dist: black>=23.0.0; extra == "dev"
Requires-Dist: ruff>=0.1.0; extra == "dev"
Dynamic: author
Dynamic: home-page
Dynamic: license-file
Dynamic: requires-python
